groundcontrolsh/__init__.py
groundcontrolsh/groundcontrolsh.py
groundcontrolsh/py.typed
groundcontrolsh-0.3.0.dist-info/METADATA
groundcontrolsh-0.3.0.dist-info/WHEEL
groundcontrolsh-0.3.0.dist-info/top_level.txt
groundcontrolsh-0.3.0.dist-info/RECORD
