Metadata-Version: 2.1
Name: groundcontrolsh
Version: 0.3.0
Classifier: Development Status :: 4 - Beta
Classifier: License :: OSI Approved :: MIT License
Classifier: Natural Language :: English
Classifier: Operating System :: OS Independent
Classifier: Programming Language :: Python
Classifier: Programming Language :: Python :: 3.8
Classifier: Programming Language :: Python :: 3.9
Requires-Python: >=3
Requires-Dist: requests (<3.0.0dev,>=2.5.0)
Provides-Extra: dev
Requires-Dist: pylint (~=2.14.0) ; extra == 'dev'
Requires-Dist: toml (~=0.10.2) ; extra == 'dev'
Requires-Dist: yapf (~=0.32.0) ; extra == 'dev'
